pytradier/__init__.py
pytradier/models.py
pytradier/tradier_api.py
pytradier-0.1.0.dist-info/LICENSE
pytradier-0.1.0.dist-info/METADATA
pytradier-0.1.0.dist-info/WHEEL
pytradier-0.1.0.dist-info/top_level.txt
pytradier-0.1.0.dist-info/RECORD
