Metadata-Version: 2.1
Name: pytradier
Version: 0.1.0
Summary: Python client for tradier API
Home-page: https://github.com/Etienne-larchet/pytradier
Author: Etienne LARCHET
License: MIT License
Classifier: License :: OSI Approved :: MIT License
Classifier: Programming Language :: Python :: 3
Classifier: Development Status :: 2 - Pre-Alpha
License-File: LICENSE
Requires-Dist: requests
Requires-Dist: pydantic
Requires-Dist: pandas
Requires-Dist: tqdm
